<?xml version="1.0" encoding="utf-8" ?>

<problem
   package = "ru.ejudge.sample_contest"
   id = "B"
   type = "standard">
  <statement language="ru_RU">
    <title>Эпический летний роман.</title>
    <description>
        <p>
            Во время летних каникул в Гравити Фолз Мэйбл хочет завести "эпический летний роман" и вскоре к ней приходит её новый парень по имени Норман, которого Диппер считает зомби и отчаянно пытается доказать это сестре. Оставшись наедине с Мэйбл, Норман признается, что он на самом деле толпа гномов, ищущих себе королеву. Джефф - главный и самый высокий гном - делает предложение Мэйбл, от которого она отказывается. Разозленный Джефф собирает всех гномов для преследования Мэйбл и они преобразуются в гигантского монстра, для превращения в которого им нужно выстроиться по росту.
</p> <br/>
<p>
    <b>Входные данные:</b><br/>
    В первой строке вам дано натуральное число N(0 &lt; N &lt; 100) - количество гномов под управлением Джеффа.<br/>
    Далее описан рост каждого из гномов, рост - это положительное число до 100.
</p>
<br/>
<p>
    <b>Выходные данные:</b><br/>
   Помогите Джеффу построить всех гномов по росту так, чтобы самый высокий гном стоял первым, а самый низкий последним (т.е. по убыванию роста гнома).
</p><br/>
    </description>
  </statement>
  <examples>
    <example>
        <input>
       4
 1 2 3 4
</input>
<output>
 4 3 2 1
</output>
    </example>
  </examples>
</problem>
